snapctl/__init__.py
snapctl/__main__.py
snapctl/commands/__init__.py
snapctl/commands/application.py
snapctl/commands/byogs.py
snapctl/commands/byosnap.py
snapctl/commands/byows.py
snapctl/commands/game.py
snapctl/commands/generate.py
snapctl/commands/release_notes.py
snapctl/commands/snapend.py
snapctl/commands/snapend_manifest.py
snapctl/commands/snaps.py
snapctl/config/__init__.py
snapctl/config/app.py
snapctl/config/constants.py
snapctl/config/endpoints.py
snapctl/config/hashes.py
snapctl/data/__init__.py
snapctl/data/profiles/__init__.py
snapctl/data/profiles/snapser-byosnap-profile.json
snapctl/data/profiles/snapser-byosnap-profile.yaml
snapctl/data/profiles/snapser-byosnap-profile.yml
snapctl/data/releases/1.0.0.mdx
snapctl/data/releases/1.0.2.mdx
snapctl/data/releases/1.0.3.mdx
snapctl/data/releases/1.0.4.mdx
snapctl/data/releases/1.1.0.mdx
snapctl/data/releases/1.1.2.mdx
snapctl/data/releases/1.1.3.mdx
snapctl/data/releases/1.1.4.mdx
snapctl/data/releases/1.1.5.mdx
snapctl/data/releases/1.4.0.mdx
snapctl/data/releases/1.4.1.mdx
snapctl/data/releases/__init__.py
snapctl/data/releases/beta-0.46.0.mdx
snapctl/data/releases/beta-0.46.4.mdx
snapctl/data/releases/beta-0.47.0.mdx
snapctl/data/releases/beta-0.47.1.mdx
snapctl/data/releases/beta-0.47.2.mdx
snapctl/data/releases/beta-0.48.0.mdx
snapctl/data/releases/beta-0.49.0.mdx
snapctl/data/releases/beta-0.49.1.mdx
snapctl/data/releases/beta-0.49.2.mdx
snapctl/data/releases/beta-0.49.3.mdx
snapctl/data/releases/beta-0.50.0.mdx
snapctl/data/releases/beta-0.51.0.mdx
snapctl/data/releases/beta-0.53.1.mdx
snapctl/main.py
snapctl/types/__init__.py
snapctl/types/definitions.py
snapctl/utils/__init__.py
snapctl/utils/echo.py
snapctl/utils/exceptions.py
snapctl/utils/helper.py
snapctl/utils/telemetry.py
snapctl-1.4.1.dist-info/LICENSE
snapctl-1.4.1.dist-info/METADATA
snapctl-1.4.1.dist-info/WHEEL
snapctl-1.4.1.dist-info/entry_points.txt
snapctl-1.4.1.dist-info/RECORD
