Metadata-Version: 2.1
Name: snapctl
Version: 1.4.1
Summary: Snapser CLI Tool
Author: Ajinkya Apte
Author-email: aj@snapser.com
Requires-Python: >=3.10,<3.15
Classifier: Programming Language :: Python :: 3
Classifier: Programming Language :: Python :: 3.10
Classifier: Programming Language :: Python :: 3.11
Classifier: Programming Language :: Python :: 3.12
Provides-Extra: all
Requires-Dist: configparser (>=6,<7)
Requires-Dist: pyfiglet (>=1.0.2,<2.0.0)
Requires-Dist: pyyaml (>=6.0.2,<7.0.0)
Requires-Dist: requests (>=2.28.2,<3.0.0)
Requires-Dist: rich (>=13) ; extra == "all"
Requires-Dist: shellingham (>=1.5) ; extra == "all"
Requires-Dist: typer (>=0.18,<1.0)
